setup.py
phantomjs_packages/__init__.py
phantomjs_packages/main.py
phantomjs_packages.egg-info/PKG-INFO
phantomjs_packages.egg-info/SOURCES.txt
phantomjs_packages.egg-info/dependency_links.txt
phantomjs_packages.egg-info/top_level.txt