Metadata-Version: 2.1
Name: phantomjs-packages
Version: 1.0.0
Summary: Phantomjs packages for different systems.
Home-page: https://github.com/jtc1246
Author: Tiancheng Jiao
Author-email: jtc1246@outlook.com
License: GPL-2.0 License
Platform: all
Requires-Python: >=3
